src/Lat2D_mattb242/Lat2Dv2.py
src/Lat2D_mattb242/__init__.py
flatlat-2.0.0.dist-info/METADATA
flatlat-2.0.0.dist-info/WHEEL
flatlat-2.0.0.dist-info/licenses/LICENSE
flatlat-2.0.0.dist-info/RECORD
