Metadata-Version: 2.1
Name: FlatLat
Version: 2.0.0
Summary: A Package for Calculating 2D Lattice Invariants
Project-URL: Homepage, https://github.com/MattB-242/Lattice_Invariance
Author-email: Matt Bright <mattbright1974@gmail.com>
License: MIT License
License-File: LICENSE
Classifier: License :: OSI Approved :: MIT License
Classifier: Operating System :: OS Independent
Classifier: Programming Language :: Python :: 3
Requires-Python: >=3.7
